{"cameraMode":{"drawMode":0,"name":"Shaded","section":"Shading Mode"},"sceneLighting":true,"audioPlay":false,"sceneViewState":{"m_AlwaysRefresh":false,"showFog":true,"showSkybox":true,"showFlares":true,"showImageEffects":true,"showParticleSystems":true,"showVisualEffectGraphs":true,"m_FxEnabled":true},"in2DMode":false,"pivot":{"x":-1.0306544303894044,"y":0.5901787877082825,"z":3.294250965118408},"rotation":{"x":-0.13456778228282929,"y":-0.1318831890821457,"z":-0.018050983548164369,"w":0.9819464683532715},"size":2.317823648452759,"orthographic":false}